adani/__init__.py
adani/_core.cpython-38-x86_64-linux-gnu.so
adani/_version.py
adani.libs/libgfortran-040039e1.so.5.0.0
adani.libs/libgsl-dc19e51b.so.28.0.0
adani.libs/libgslcblas-d9249d76.so.0.0.0
adani.libs/libquadmath-96973f99.so.0.0.0
adani-1.0.5.dist-info/LICENSE
adani-1.0.5.dist-info/METADATA
adani-1.0.5.dist-info/WHEEL
adani-1.0.5.dist-info/top_level.txt
adani-1.0.5.dist-info/RECORD
