Metadata-Version: 2.4
Name: adani
Version: 1.0.5
Summary: Code computing approximate DIS N3LO coefficients
Author: Niccolò Laurenti
License: AGPLv3
Requires-Python: >=3.8
License-File: LICENSE
Dynamic: author
Dynamic: description
Dynamic: description-content-type
Dynamic: license
Dynamic: license-file
Dynamic: requires-python
Dynamic: summary
